ai_helper/__init__.py
ai_helper/cli.py
ai_helper/core.py
ai_helper/providers/base.py
ai_helper/providers/gemini.py
ai_helper/providers/local.py
ai_helper/providers/openai.py
csai_helper-0.1.2.dist-info/licenses/LICENSE
csai_helper-0.1.2.dist-info/METADATA
csai_helper-0.1.2.dist-info/WHEEL
csai_helper-0.1.2.dist-info/entry_points.txt
csai_helper-0.1.2.dist-info/top_level.txt
csai_helper-0.1.2.dist-info/RECORD
