Metadata-Version: 2.4
Name: csai-helper
Version: 0.1.2
Summary: Lightweight helpers for AI prompts, summarization, and formatting.
Author-email: Your Name <you@example.com>
License-Expression: MIT
Requires-Python: >=3.9
License-File: LICENSE
Requires-Dist: typing-extensions>=4.8
Requires-Dist: requests>=2.31
Provides-Extra: openai
Requires-Dist: openai>=1.47; extra == "openai"
Provides-Extra: dev
Requires-Dist: pytest>=7.4; extra == "dev"
Requires-Dist: pytest-cov>=4.1; extra == "dev"
Requires-Dist: ruff>=0.5; extra == "dev"
Requires-Dist: pre-commit>=3.6; extra == "dev"
Dynamic: license-file
